deribit_data_scrapper/__init__.py
deribit_data_scrapper/DataBase/AbstractDataSaverManager.py
deribit_data_scrapper/DataBase/HDF5NewDaemon.py
deribit_data_scrapper/DataBase/MySQLNewDaemon.py
deribit_data_scrapper/DataBase/__init__.py
deribit_data_scrapper/ExternalModules/AbstractExternal.py
deribit_data_scrapper/ExternalModules/__init__.py
deribit_data_scrapper/ExternalModules/ExternalLib/SabrCalibration.py
deribit_data_scrapper/ExternalModules/ExternalLib/TestDash.py
deribit_data_scrapper/ExternalModules/ExternalLib/__init__.py
deribit_data_scrapper/InstrumentManager/AbstractInstrument.py
deribit_data_scrapper/InstrumentManager/InstrumentManager.py
deribit_data_scrapper/InstrumentManager/__init__.py
deribit_data_scrapper/InstrumentManager/testAbstractInstrument.py
deribit_data_scrapper/OrderManager/OrderManager.py
deribit_data_scrapper/OrderManager/__init__.py
deribit_data_scrapper/Scrapper/ScrapperWithPreSelectedMaturities.py
deribit_data_scrapper/Scrapper/TradingInterface.py
deribit_data_scrapper/Scrapper/__init__.py
deribit_data_scrapper/Strategy/AbstractStrategy.py
deribit_data_scrapper/Strategy/BasicStrategy.py
deribit_data_scrapper/Strategy/EmptyStrategy.py
deribit_data_scrapper/Strategy/__init__.py
deribit_data_scrapper/Subsciption/AbstractSubscription.py
deribit_data_scrapper/Subsciption/NullSubscription.py
deribit_data_scrapper/Subsciption/OrderBookSubscriptionLimitedDepth.py
deribit_data_scrapper/Subsciption/OwnOrderUpdate.py
deribit_data_scrapper/Subsciption/TradesSubscription.py
deribit_data_scrapper/Subsciption/UserPortfolioChanges.py
deribit_data_scrapper/Subsciption/__init__.py
deribit_data_scrapper/SyncLib/AvailableRequests.py
deribit_data_scrapper/SyncLib/CreateOptionSurface.py
deribit_data_scrapper/SyncLib/DeribitConnectionOld.py
deribit_data_scrapper/SyncLib/DownloadOptionWithIndexPrice.py
deribit_data_scrapper/SyncLib/Scrapper.py
deribit_data_scrapper/SyncLib/__init__.py
deribit_data_scrapper/Utils/AvailableConfigurationRoot.py
scrapperDeribit-0.0.31.dist-info/LICENSE.txt
scrapperDeribit-0.0.31.dist-info/METADATA
scrapperDeribit-0.0.31.dist-info/WHEEL
scrapperDeribit-0.0.31.dist-info/top_level.txt
scrapperDeribit-0.0.31.dist-info/RECORD
